Himpunan_Team1/Himpunan_Team1.py
Himpunan_Team1/__init__.py
himpunan_team1-0.2.0.dist-info/LICENSE
himpunan_team1-0.2.0.dist-info/METADATA
himpunan_team1-0.2.0.dist-info/WHEEL
himpunan_team1-0.2.0.dist-info/top_level.txt
himpunan_team1-0.2.0.dist-info/RECORD
